LICENSE
MANIFEST.in
README.md
setup.cfg
setup.py
django_mp_shop_offers.egg-info/PKG-INFO
django_mp_shop_offers.egg-info/SOURCES.txt
django_mp_shop_offers.egg-info/dependency_links.txt
django_mp_shop_offers.egg-info/top_level.txt
offers/__init__.py
offers/admin.py
offers/forms.py
offers/lib.py
offers/models.py
offers/urls.py
offers/views.py
offers/locale/ru/LC_MESSAGES/django.mo
offers/locale/ru/LC_MESSAGES/django.po
offers/locale/uk/LC_MESSAGES/django.mo
offers/locale/uk/LC_MESSAGES/django.po
offers/migrations/0001_initial.py
offers/migrations/__init__.py
offers/static/jquery.maskedinput.js
offers/static/offers/offers.js
offers/templates/offers/price_offer_form.html
offers/templates/offers/price_offer_modal.html
offers/templates/offers/notifications/email.html
offers/templates/offers/notifications/sms.txt