Metadata-Version: 2.1
Name: django-mp-shop-offers
Version: 2.0.1
Summary: Django shop offers app
Home-page: https://github.com/pmaigutyak/mp-shop-offers
Author: Paul Maigutyak
Author-email: pmaigutyak@gmail.com
License: MIT
Download-URL: https://github.com/pmaigutyak/mp-shop-offers/archive/2.0.1.tar.gz
Platform: UNKNOWN
License-File: LICENSE
